README.md
setup.py
TeleNex.egg-info/PKG-INFO
TeleNex.egg-info/SOURCES.txt
TeleNex.egg-info/dependency_links.txt
TeleNex.egg-info/requires.txt
TeleNex.egg-info/top_level.txt
teleNex/__init__.py
teleNex/helpers.py
teleNex/bot/__init__.py
teleNex/bot/base.py
teleNex/bot/bot.py
teleNex/types/__init__.py
teleNex/types/base.py
teleNex/types/callback_query.py
teleNex/types/chat.py
teleNex/types/document.py
teleNex/types/field.py
teleNex/types/file.py
teleNex/types/login_url.py
teleNex/types/mask_position.py
teleNex/types/message.py
teleNex/types/message_entity.py
teleNex/types/photo_size.py
teleNex/types/response.py
teleNex/types/sticker.py
teleNex/types/update.py
teleNex/types/user.py
teleNex/types/keyboard/__init__.py
teleNex/types/keyboard/base.py
teleNex/types/keyboard/inline_keyboard.py
teleNex/types/keyboard/reply_keyboard.py