Metadata-Version: 2.1
Name: TeleNex
Version: 0.0.11
Summary: TeleNex - это Frimework для простого создания асинхронных Telegram ботов
Home-page: https://github.com/inex550/TeleNex
Author: iNex
Author-email: inex552@gmail.com
License: UNKNOWN
Platform: UNKNOWN
Classifier: Programming Language :: Python :: 3
Classifier: License :: OSI Approved :: MIT License
Classifier: Operating System :: OS Independent
Requires-Python: >=3.7
